MANIFEST.in
README.rst
setup.py
tgext/__init__.py
tgext.ajaxforms.egg-info/PKG-INFO
tgext.ajaxforms.egg-info/SOURCES.txt
tgext.ajaxforms.egg-info/dependency_links.txt
tgext.ajaxforms.egg-info/entry_points.txt
tgext.ajaxforms.egg-info/namespace_packages.txt
tgext.ajaxforms.egg-info/not-zip-safe
tgext.ajaxforms.egg-info/requires.txt
tgext.ajaxforms.egg-info/top_level.txt
tgext/ajaxforms/__init__.py
tgext/ajaxforms/ajaxform.py
tgext/ajaxforms/tw_compat.py
tgext/ajaxforms/statics/jquery.form.js
tgext/ajaxforms/statics/jquery.min.js
tgext/ajaxforms/statics/spinner.gif
tgext/ajaxforms/templates/__init__.py
tgext/ajaxforms/templates/ajaxform.html
tgext/ajaxforms/templates/ajaxform.xhtml