Metadata-Version: 1.1
Name: tgext.ajaxforms
Version: 0.3.2
Summary: Makes easier to create AJAX forms in TurboGears2
Home-page: http://bitbucket.org/_amol_/tgext.ajaxforms
Author: Alessandro Molina
Author-email: alessandro.molina@axant.it
License: MIT
Keywords: turbogears2.extension
Platform: UNKNOWN
Classifier: Environment :: Web Environment
Classifier: Topic :: Software Development :: Libraries :: Python Modules
Classifier: Framework :: TurboGears
